MANIFEST.in
liqui.py
readme.md
setup.py
liqui.egg-info/PKG-INFO
liqui.egg-info/SOURCES.txt
liqui.egg-info/dependency_links.txt
liqui.egg-info/requires.txt
liqui.egg-info/top_level.txt