Metadata-Version: 1.0
Name: liqui
Version: 1.0.1
Summary: liqui.io api wrapper
Home-page: https://github.com/banteg/liqui
Author: banteg
Author-email: UNKNOWN
License: MIT
Platform: UNKNOWN
